natural_frontend/__init__.py
natural_frontend/cache.py
natural_frontend/constants.py
natural_frontend/framework_helpers.py
natural_frontend/frontend_generator.py
natural_frontend/natural_frontend.py
natural_frontend/natural_frontend_options.py
natural_frontend/static/natural_frontend_logo.png
natural_frontend/templates/queryForm.html
natural_frontend-0.1.1.dist-info/METADATA
natural_frontend-0.1.1.dist-info/WHEEL
natural_frontend-0.1.1.dist-info/licenses/LICENSE
natural_frontend-0.1.1.dist-info/RECORD
