Metadata-Version: 2.1
Name: natural-frontend
Version: 0.1.1
Summary: A wrapper for FastAPI to automatically generate a frontend
Project-URL: Homepage, https://github.com/axelpey/natural-frontend
Project-URL: Issues, https://github.com/axelpey/natural-frontend/issues
Author-email: Axel Peytavin <peytavin@stanford.edu>, Pierre Collignon <collignonpie@gmail.com>
License-File: LICENSE
Classifier: License :: OSI Approved :: MIT License
Classifier: Operating System :: OS Independent
Classifier: Programming Language :: Python :: 3
Requires-Python: >=3.8
Requires-Dist: jinja2>=3.1.3
Requires-Dist: openai>=1.8.0
Requires-Dist: python-multipart>=0.0.6
